MEDS_visualizations/__init__.py
MEDS_visualizations/types.py
MEDS_visualizations/visualization.py
MEDS_visualizations/extractors/__init__.py
MEDS_visualizations/extractors/active_subjects.py
MEDS_visualizations/extractors/base.py
MEDS_visualizations/extractors/code_frequency.py
MEDS_visualizations/extractors/measurement_density.py
MEDS_visualizations/extractors/meds_pl_mixin.py
MEDS_visualizations/plotters/__init__.py
MEDS_visualizations/plotters/bar.py
MEDS_visualizations/plotters/base.py
MEDS_visualizations/plotters/density_heatmap.py
MEDS_visualizations/plotters/line.py
meds_visualizations-0.0.5.dist-info/licenses/LICENSE
meds_visualizations-0.0.5.dist-info/METADATA
meds_visualizations-0.0.5.dist-info/WHEEL
meds_visualizations-0.0.5.dist-info/top_level.txt
meds_visualizations-0.0.5.dist-info/RECORD
