Metadata-Version: 2.4
Name: MEDS_visualizations
Version: 0.0.5
Summary: A framework for compiling simple, mapreduce style pipelines over MEDS datasets.
Author-email: Matthew McDermott <mattmcdermott8@gmail.com>
Project-URL: Homepage, https://github.com/mmcdermott/MEDS_visualizations
Project-URL: Issues, https://github.com/mmcdermott/MEDS_visualizations/issues
Classifier: Programming Language :: Python :: 3
Classifier: License :: OSI Approved :: MIT License
Classifier: Operating System :: OS Independent
Requires-Python: >=3.11
License-File: LICENSE
Requires-Dist: polars<=1.27.9,>=1.26.0
Requires-Dist: plotly
Requires-Dist: meds~=0.4.0
Requires-Dist: jupyter
Provides-Extra: dev
Requires-Dist: pre-commit<4; extra == "dev"
Requires-Dist: ruff; extra == "dev"
Provides-Extra: tests
Requires-Dist: pytest-cov; extra == "tests"
Requires-Dist: pytest; extra == "tests"
Requires-Dist: meds_testing_helpers~=0.3.0; extra == "tests"
Dynamic: license-file
